
{
  "admins": {
    "jyuqnOk9R2V1aMCJLs5RFZGBFdV2": true
  },
  "camps": {
    "autumn-retreat-2024": {
      "activities": [
        "Photography",
        "Yoga",
        "Foliage Walks"
      ],
      "date": "October 10-14, 2024",
      "description": "A relaxing retreat focused on photography, yoga, and enjoying the stunning autumn foliage.",
      "id": "autumn-retreat-2024",
      "image": {
        "id": "gallery-8",
        "imageHint": "autumn valley",
        "imageUrl": "https://images.unsplash.com/photo-1634252803091-a50d3111b329?crop=entropy&cs=tinysrgb&fit=max&fm=jpg&ixid=M3w3NDE5ODJ8MHwxfHNlYXJjaHw0fHxhdXR1bW4lMjB2YWxsZXl8ZW58MHx8fHwxNzU5MDU2MjQ1fDA&ixlib=rb-4.1.0&q=80&w=1080"
      },
      "location": "Maple Valley",
      "name": "Autumn Colors Retreat",
      "price": 18000
    },
    "coastal-survival-2024": {
      "activities": [
        "Foraging",
        "Fishing",
        "Shelter Building"
      ],
      "date": "September 2-7, 2024",
      "description": "Learn to forage, fish, and build shelters on the beautiful but rugged coastline.",
      "id": "coastal-survival-2024",
      "image": {
        "id": "gallery-9",
        "imageHint": "coastal camping",
        "imageUrl": "https://images.unsplash.com/photo-1630084879730-bbcd06b0778e?crop=entropy&cs=tinysrgb&fit=max&fm=jpg&ixid=M3w3NDE5ODJ8MHwxfHNlYXJjaHwxMHx8Y29hc3RhbCUyMGNhbXBpbmd8ZW58MHx8fHwxNzU5MjE5OTE4fDA&ixlib=rb-4.1.0&q=80&w=1080"
      },
      "location": "Shipwreck Cove",
      "name": "Coastal Survival Skills",
      "price": 22000
    },
    "mountain-explorer-2024": {
      "activities": [
        "Rock Climbing",
        "Trekking",
        "High-Altitude Training"
      ],
      "date": "August 5-12, 2024",
      "description": "Challenge yourself with advanced rock climbing and high-altitude trekking. For experienced adventurers.",
      "id": "mountain-explorer-2024",
      "image": {
        "id": "gallery-2",
        "imageHint": "mountain summit",
        "imageUrl": "https://images.unsplash.com/photo-1534685785745-60a2cea0ec34?crop=entropy&cs=tinysrgb&fit=max&fm=jpg&ixid=M3w3NDE5ODJ8MHwxfHNlYXJjaHwyfHxtb3VudGFpbiUyMHN1bW1pdHxlbnwwfHx8fDE3NTkxNDgxMDl8MA&ixlib=rb-4.1.0&q=80&w=1080"
      },
      "location": "Granite Peak National Park",
      "name": "Mountain Explorer",
      "price": 25000
    },
    "summer-adventure-2024": {
      "activities": [
        "Hiking",
        "Bonfires",
        "Lake Swimming"
      ],
      "date": "July 15-20, 2024",
      "description": "A classic summer camp experience with hiking, bonfires, and lake swimming. Perfect for all ages.",
      "id": "summer-adventure-2024",
      "image": {
        "id": "gallery-1",
        "imageHint": "mountain lake",
        "imageUrl": "https://images.unsplash.com/photo-1530173660394-4047e55984d1?crop=entropy&cs=tinysrgb&fit=max&fm=jpg&ixid=M3w3NDE5ODJ8MHwxfHNlYXJjaHw0fHxtb3VudGFpbiUyMGxha2V8ZW58MHx8fHwxNzU5MTQ5Nzc4fDA&ixlib=rb-4.1.0&q=80&w=1080"
      },
      "location": "Whispering Pines Forest",
      "name": "Summer Adventure Camp",
      "price": 15000
    }
  },
  "galleryImages": {
    "gallery-1": {
      "description": "A serene mountain lake reflecting the sunrise.",
      "id": "gallery-1",
      "imageHint": "mountain lake",
      "imageUrl": "https://images.unsplash.com/photo-1530173660394-4047e55984d1?crop=entropy&cs=tinysrgb&fit=max&fm=jpg&ixid=M3w3NDE5ODJ8MHwxfHNlYXJjaHw0fHxtb3VudGFpbiUyMGxha2V8ZW58MHx8fHwxNzU5MTQ5Nzc4fDA&ixlib=rb-4.1.0&q=80&w=1080"
    },
    "gallery-2": {
      "description": "Hikers celebrating on a mountain summit.",
      "id": "gallery-2",
      "imageHint": "mountain summit",
      "imageUrl": "https://images.unsplash.com/photo-1534685785745-60a2cea0ec34?crop=entropy&cs=tinysrgb&fit=max&fm=jpg&ixid=M3w3NDE5ODJ8MHwxfHNlYXJjaHwyfHxtb3VudGFpbiUyMHN1bW1pdHxlbnwwfHx8fDE3NTkxNDgxMDl8MA&ixlib=rb-4.1.0&q=80&w=1080"
    },
    "gallery-3": {
      "description": "A cozy campfire with friends sharing stories.",
      "id": "gallery-3",
      "imageHint": "campfire friends",
      "imageUrl": "https://images.unsplash.com/photo-1661758211116-388aae0197f0?crop=entropy&cs=tinysrgb&fit=max&fm=jpg&ixid=M3w3NDE5ODJ8MHwxfHNlYXJjaHw4fHxjYW1wZmlyZSUyMGZyaWVuZHN8ZW58MHx8fHwxNzU5MDk2Njg1fDA&ixlib=rb-4.1.0&q=80&w=1080"
    },
    "gallery-4": {
      "description": "Kayaking on a calm, misty river at dawn.",
      "id": "gallery-4",
      "imageHint": "kayaking river",
      "imageUrl": "https://images.unsplash.com/photo-1710702417437-d898ee99f9bf?crop=entropy&cs=tinysrgb&fit=max&fm=jpg&ixid=M3w3NDE5ODJ8MHwxfHNlYXJjaHw5fHxrYXlha2luZyUyMHJpdmVyfGVufDB8fHx8MTc1ODk1NDU3M3ww&ixlib=rb-4.1.0&q=80&w=1080"
    },
    "gallery-8": {
      "description": "Stunning autumn foliage in a vast valley.",
      "id": "gallery-8",
      "imageHint": "autumn valley",
      "imageUrl": "https://images.unsplash.com/photo-1634252803091-a50d3111b329?crop=entropy&cs=tinysrgb&fit=max&fm=jpg&ixid=M3w3NDE5ODJ8MHwxfHNlYXJjaHw0fHxhdXR1bW4lMjB2YWxsZXl8ZW58MHx8fHwxNzU5MDU2MjQ1fDA&ixlib=rb-4.1.0&q=80&w=1080"
    },
    "gallery-9": {
      "description": "A group of tents pitched by a rugged coastline.",
      "id": "gallery-9",
      "imageHint": "coastal camping",
      "imageUrl": "https://images.unsplash.com/photo-1630084879730-bbcd06b0778e?crop=entropy&cs=tinysrgb&fit=max&fm=jpg&ixid=M3w3NDE5ODJ8MHwxfHNlYXJjaHwxMHx8Y29hc3RhbCUyMGNhbXBpbmd8ZW58MHx8fHwxNzU5MjE5OTE4fDA&ixlib=rb-4.1.0&q=80&w=1080"
    }
  },
  "users": {
    "5o1RmpE2MgZBEsgeKGQi4EL35KD2": {
      "bookings": {
        "-OacZFBB0ku2lUNTkBSr": {
          "bookingDate": "2025-10-03T05:34:59.803Z",
          "campId": "summer-adventure-2024",
          "campName": "Summer Adventure Camp",
          "numberOfPeople": 2,
          "status": "Approved",
          "userId": "5o1RmpE2MgZBEsgeKGQi4EL35KD2"
        }
      },
      "email": "abhishek@mail.com",
      "firstName": "Abhishek",
      "history": {
        "1759469593731": {
          "description": "Account created",
          "timestamp": "2025-10-03T05:33:13.731Z",
          "type": "signup"
        },
        "-OacZFBB0ku2lUNTkBSr": {
          "description": "Booked Summer Adventure Camp",
          "timestamp": "2025-10-03T05:34:59.803Z",
          "type": "booking"
        }
      },
      "lastName": "Sharma",
      "messages": {
        "-Oad123abc": {
          "read": true,
          "subject": "Question about camp food",
          "timestamp": "2025-10-04T10:00:00.000Z"
        }
      },
      "phone": "8355855988",
      "photoURL": ""
    },
    "jyuqnOk9R2V1aMCJLs5RFZGBFdV2": {
      "email": "i.am.racer.s@gmail.com",
      "firstName": "Admin",
      "history": {
        "1759469593732": {
          "description": "Account created by admin",
          "timestamp": "2025-10-03T06:00:00.000Z",
          "type": "signup"
        }
      },
      "lastName": "User",
      "phone": "",
      "photoURL": ""
    }
  }
}
